LICENSE.txt
MANIFEST.in
README.md
setup.py
animo_trainer/__init__.py
animo_trainer/animo_env.py
animo_trainer/animo_stats_writers.py
animo_trainer/animo_torch_model_saver.py
animo_trainer/animo_trainer_controller.py
animo_trainer/animo_training_session.py
animo_trainer/main.py
animo_trainer/typed_numpy.py
animo_trainer/version.py
animo_trainer.egg-info/PKG-INFO
animo_trainer.egg-info/SOURCES.txt
animo_trainer.egg-info/dependency_links.txt
animo_trainer.egg-info/entry_points.txt
animo_trainer.egg-info/requires.txt
animo_trainer.egg-info/top_level.txt
animo_trainer/lib/AnimoSimulation.deps.json
animo_trainer/lib/AnimoSimulation.dll
animo_trainer/lib/AnimoSimulation.pdb
animo_trainer/lib/Newtonsoft.Json.dll
animo_trainer/lib/System.Buffers.dll
animo_trainer/lib/System.Memory.dll
animo_trainer/lib/System.Numerics.Vectors.dll
animo_trainer/lib/System.Runtime.CompilerServices.Unsafe.dll
tests/test_simulate.py
typings/clr.pyi
typings/Internal/__init__.pyi
typings/Internal/Runtime/CompilerServices/__init__.pyi
typings/Internal/Runtime/InteropServices/__init__.pyi
typings/Microsoft/Win32/SafeHandles/__init__.pyi
typings/System/__init__.pyi
typings/System/Buffers/__init__.pyi
typings/System/Buffers/Binary/__init__.pyi
typings/System/Buffers/Text/__init__.pyi
typings/System/CodeDom/Compiler/__init__.pyi
typings/System/Collections/__init__.pyi
typings/System/Collections/Concurrent/__init__.pyi
typings/System/Collections/Generic/__init__.pyi
typings/System/Collections/ObjectModel/__init__.pyi
typings/System/ComponentModel/__init__.pyi
typings/System/Configuration/Assemblies/__init__.pyi
typings/System/Diagnostics/__init__.pyi
typings/System/Diagnostics/CodeAnalysis/__init__.pyi
typings/System/Diagnostics/Contracts/__init__.pyi
typings/System/Diagnostics/SymbolStore/__init__.pyi
typings/System/Diagnostics/Tracing/__init__.pyi
typings/System/Globalization/__init__.pyi
typings/System/IO/__init__.pyi
typings/System/IO/Enumeration/__init__.pyi
typings/System/Net/__init__.pyi
typings/System/Numerics/__init__.pyi
typings/System/Reflection/__init__.pyi
typings/System/Reflection/Emit/__init__.pyi
typings/System/Reflection/Metadata/__init__.pyi
typings/System/Resources/__init__.pyi
