Metadata-Version: 2.1
Name: animo-trainer
Version: 1.0.0
Summary: Animo Trainer
Home-page: https://transforms.ai/
Author: Transitional Forms
Author-email: dante@transforms.ai
License: Copyright (c) 2023 Transitional Forms Inc. All Rights Reserved.
Requires-Python: >=3.9,<3.10
License-File: LICENSE.txt
Requires-Dist: protobuf==3.20
Requires-Dist: mlagents==0.30.0
Requires-Dist: pythonnet==3.0.1
Requires-Dist: torch==1.11.0
Requires-Dist: psutil
